vnv/__init__.py
vnv/cli.py
vnv/lists.py
vnv/meta.py
vnv/python.py
vnv/shell_compat.py
vnv-1.2.data/scripts/vnv
vnv-1.2.data/scripts/vnv-do-finish.csh
vnv-1.2.data/scripts/vnv-startup
vnv-1.2.data/scripts/vnv-startup.csh
vnv-1.2.data/scripts/vnv-startup.fish
vnv-1.2.data/scripts/vnv-startup.xsh
vnv-1.2.data/scripts/vnv.bat
vnv-1.2.data/scripts/vnv.ps1
vnv-1.2.dist-info/METADATA
vnv-1.2.dist-info/UNLICENSE
vnv-1.2.dist-info/WHEEL
vnv-1.2.dist-info/entry_points.txt
vnv-1.2.dist-info/top_level.txt
vnv-1.2.dist-info/RECORD
